async_reolink/rest/__init__.py
async_reolink/rest/__version__.py
async_reolink/rest/connection.py
async_reolink/rest/errors.py
async_reolink/rest/models.py
async_reolink/rest/typings.py
async_reolink/rest/_utilities/__init__.py
async_reolink/rest/_utilities/dictlist.py
async_reolink/rest/_utilities/repr.py
async_reolink/rest/ai/__init__.py
async_reolink/rest/ai/models.py
async_reolink/rest/ai/typings.py
async_reolink/rest/alarm/__init__.py
async_reolink/rest/commands/__init__.py
async_reolink/rest/commands/ai.py
async_reolink/rest/commands/alarm.py
async_reolink/rest/commands/encoding.py
async_reolink/rest/commands/led.py
async_reolink/rest/commands/network.py
async_reolink/rest/commands/ptz.py
async_reolink/rest/commands/record.py
async_reolink/rest/commands/security.py
async_reolink/rest/commands/system.py
async_reolink/rest/encoding/__init__.py
async_reolink/rest/encoding/models.py
async_reolink/rest/encoding/typings.py
async_reolink/rest/led/__init__.py
async_reolink/rest/led/models.py
async_reolink/rest/led/typings.py
async_reolink/rest/network/__init__.py
async_reolink/rest/network/models.py
async_reolink/rest/network/typings.py
async_reolink/rest/ptz/__init__.py
async_reolink/rest/ptz/models.py
async_reolink/rest/ptz/typings.py
async_reolink/rest/record/__init__.py
async_reolink/rest/record/models.py
async_reolink/rest/record/seed.py
async_reolink/rest/security/__init__.py
async_reolink/rest/security/models.py
async_reolink/rest/security/typings.py
async_reolink/rest/system/__init__.py
async_reolink/rest/system/capabilities.py
async_reolink/rest/system/models.py
async_reolink/rest/system/typings.py
async_reolink/rest/video/__init__.py
async_reolink.rest-0.6.6.dist-info/METADATA
async_reolink.rest-0.6.6.dist-info/WHEEL
async_reolink.rest-0.6.6.dist-info/top_level.txt
async_reolink.rest-0.6.6.dist-info/RECORD
