Metadata-Version: 2.1
Name: async-reolink.rest
Version: 0.6.6
Summary: Async ReoLink camera REST API for python
License: MIT
Project-URL: source, https://github.com/xannor/py_reolinkrestapi
Project-URL: tracker, https://github.com/xannor/py_reolinkrestapi/issues
Keywords: ReoLink,async,rest,api
Classifier: Development Status :: 3 - Alpha
Classifier: Intended Audience :: Developers
Classifier: Topic :: Software Development :: Build Tools
Classifier: Programming Language :: Python :: 3
Classifier: Programming Language :: Python :: 3.10
Requires-Dist: aiohttp
Requires-Dist: async-reolink.api (==0.6.6)
